odoo/addons/delivery_carrier_package_measure_required/README.rst
odoo/addons/delivery_carrier_package_measure_required/__init__.py
odoo/addons/delivery_carrier_package_measure_required/__manifest__.py
odoo/addons/delivery_carrier_package_measure_required/i18n/delivery_carrier_package_measure_required.pot
odoo/addons/delivery_carrier_package_measure_required/models/__init__.py
odoo/addons/delivery_carrier_package_measure_required/models/product_packaging.py
odoo/addons/delivery_carrier_package_measure_required/models/stock_picking.py
odoo/addons/delivery_carrier_package_measure_required/models/stock_quant_package.py
odoo/addons/delivery_carrier_package_measure_required/readme/CONTRIBUTORS.rst
odoo/addons/delivery_carrier_package_measure_required/readme/DESCRIPTION.rst
odoo/addons/delivery_carrier_package_measure_required/static/description/icon.png
odoo/addons/delivery_carrier_package_measure_required/static/description/index.html
odoo/addons/delivery_carrier_package_measure_required/tests/__init__.py
odoo/addons/delivery_carrier_package_measure_required/tests/test_delivery_carrier_package_measure_require.py
odoo/addons/delivery_carrier_package_measure_required/views/product_packaging.xml
odoo/addons/delivery_carrier_package_measure_required/wizard/__init__.py
odoo/addons/delivery_carrier_package_measure_required/wizard/choose_delivery_package.py
odoo/addons/delivery_carrier_package_measure_required/wizard/choose_delivery_package.xml
odoo14_addon_delivery_carrier_package_measure_required-14.0.1.0.2.dist-info/METADATA
odoo14_addon_delivery_carrier_package_measure_required-14.0.1.0.2.dist-info/WHEEL
odoo14_addon_delivery_carrier_package_measure_required-14.0.1.0.2.dist-info/top_level.txt
odoo14_addon_delivery_carrier_package_measure_required-14.0.1.0.2.dist-info/RECORD
